Metadata-Version: 2.1
Name: odoo14-addon-sql-export-excel
Version: 14.0.1.1.1
Summary: Allow to export a sql query to an excel file.
Home-page: https://github.com/OCA/server-tools
Author: Akretion,Odoo Community Association (OCA)
Author-email: support@odoo-community.org
License: AGPL-3
Platform: UNKNOWN
Classifier: Programming Language :: Python
Classifier: Framework :: Odoo
Classifier: Framework :: Odoo :: 14.0
Classifier: License :: OSI Approved :: GNU Affero General Public License v3
Requires-Python: >=3.6
Requires-Dist: odoo14-addon-sql-export
Requires-Dist: odoo <14.1dev,>=14.0a
Requires-Dist: openpyxl
